list_utiles/__init__.py
list_utiles/main.py
list_utilities-0.1.1.dist-info/LICENSE
list_utilities-0.1.1.dist-info/METADATA
list_utilities-0.1.1.dist-info/WHEEL
list_utilities-0.1.1.dist-info/top_level.txt
list_utilities-0.1.1.dist-info/RECORD
