Metadata-Version: 2.1
Name: list_utilities
Version: 0.1.1
Summary: A Python package for common list operations such as removing duplicates and flattening lists.
Author: Navdeep singh, Group 4
Author-email: 160320243@ggi.ac.in
Classifier: Programming Language :: Python :: 3
Classifier: License :: OSI Approved :: MIT License
Classifier: Operating System :: OS Independent
Requires-Python: >=3.6
License-File: LICENSE
